LICENSE.md
README.md
setup.py
pinata_python/__init__.py
pinata_python/base.py
pinata_python/data.py
pinata_python/gateway.py
pinata_python/pinning.py
pinata_python/users.py
pinata_python.egg-info/PKG-INFO
pinata_python.egg-info/SOURCES.txt
pinata_python.egg-info/dependency_links.txt
pinata_python.egg-info/not-zip-safe
pinata_python.egg-info/requires.txt
pinata_python.egg-info/top_level.txt
pinata_python/exceptions/__init__.py
pinata_python/exceptions/exceptions.py
pinata_python/tests/__init__.py
pinata_python/tests/conftest.py
pinata_python/tests/test_base.py
pinata_python/tests/test_data.py
pinata_python/tests/test_fixtures.py
pinata_python/tests/test_gateway.py
pinata_python/tests/test_pinning.py
pinata_python/tests/test_users.py
pinata_python/urls/__init__.py
pinata_python/urls/prefixs.py
pinata_python/utils/__init__.py
pinata_python/utils/custom_typing.py