Metadata-Version: 2.1
Name: pinata-python
Version: 1.0.0
Summary: A python API for pinata.cloud library.
Home-page: https://github.com/pan-efs/pinata-python
Author: Panagiotis Efstratiou
Author-email: 
License: MIT
Platform: UNKNOWN
Requires-Python: >=3.8
License-File: LICENSE.md
